geodn/__init__.py
geodn/GeoLite2-Country_20200616/COPYRIGHT.txt
geodn/GeoLite2-Country_20200616/GeoLite2-Country.mmdb
geodn/GeoLite2-Country_20200616/LICENSE.txt
geodn-0.20200616.2.dist-info/LICENSE
geodn-0.20200616.2.dist-info/METADATA
geodn-0.20200616.2.dist-info/WHEEL
geodn-0.20200616.2.dist-info/top_level.txt
geodn-0.20200616.2.dist-info/RECORD
